fesh2/__init__.py
fesh2/__main__.py
fesh2/_version.py
fesh2/config.py
fesh2/drudgery.py
fesh2/excluded/TestingNotes.md
fesh2/excluded/__init__.py
fesh2/excluded/requirements.txt
fesh2/excluded/setup.py
fesh2/fesh2.config
fesh2/notes.md
fesh2/notifications.py
fesh2/schedules/__init__.py
fesh2/schedules/manager.py
fesh2/schedules/server.py
fesh2/tui.py
fesh2/util/__init__.py
fesh2/util/locker.py
fesh2/util/logging.py
fesh2-2.3.2.dist-info/entry_points.txt
fesh2-2.3.2.dist-info/LICENSE
fesh2-2.3.2.dist-info/WHEEL
fesh2-2.3.2.dist-info/METADATA
fesh2-2.3.2.dist-info/RECORD
