Metadata-Version: 2.1
Name: fesh2
Version: 2.3.2
Summary: Geodetic VLBI schedule management and processing
License: GPL v3
Author: Jim Lovell
Author-email: jejlovell@gmail.com
Requires-Python: >=3.8,<4.0
Classifier: License :: Other/Proprietary License
Classifier: Programming Language :: Python :: 3
Classifier: Programming Language :: Python :: 3.10
Classifier: Programming Language :: Python :: 3.8
Classifier: Programming Language :: Python :: 3.9
Requires-Dist: ConfigArgParse (>=1.5.3,<2.0.0)
Requires-Dist: additional-urwid-widgets (>=0.4.1,<0.5.0)
Requires-Dist: numpy (>=1.23.0,<2.0.0)
Requires-Dist: pexpect (>=4.8.0,<5.0.0)
Requires-Dist: psutil (>=5.9.1,<6.0.0)
Requires-Dist: pycurl (>=7.45.1,<8.0.0)
Requires-Dist: urwid (>=2.1.2,<3.0.0)
